src/__init__.py
src/jsoniq_lsp.py
src/jsoniq_spec.py
src/package-lock.json
src/package.json
src/node_modules/.package-lock.json
src/node_modules/.bin/antlr4ng
src/node_modules/.bin/esbuild
src/node_modules/.bin/installServerIntoExtension
src/node_modules/.bin/tsx
src/node_modules/@esbuild/linux-x64/README.md
src/node_modules/@esbuild/linux-x64/package.json
src/node_modules/@esbuild/linux-x64/bin/esbuild
src/node_modules/antlr4-c3/License.txt
src/node_modules/antlr4-c3/package.json
src/node_modules/antlr4-c3/readme.md
src/node_modules/antlr4-c3/lib/index.cjs
src/node_modules/antlr4-c3/lib/index.d.ts
src/node_modules/antlr4-c3/lib/index.mjs
src/node_modules/antlr4-c3/lib/src/ArrayType.d.ts
src/node_modules/antlr4-c3/lib/src/BaseSymbol.d.ts
src/node_modules/antlr4-c3/lib/src/BlockSymbol.d.ts
src/node_modules/antlr4-c3/lib/src/ClassSymbol.d.ts
src/node_modules/antlr4-c3/lib/src/CodeCompletionCore.d.ts
src/node_modules/antlr4-c3/lib/src/DuplicateSymbolError.d.ts
src/node_modules/antlr4-c3/lib/src/FieldSymbol.d.ts
src/node_modules/antlr4-c3/lib/src/FundamentalType.d.ts
src/node_modules/antlr4-c3/lib/src/InterfaceSymbol.d.ts
src/node_modules/antlr4-c3/lib/src/LiteralSymbol.d.ts
src/node_modules/antlr4-c3/lib/src/MethodSymbol.d.ts
src/node_modules/antlr4-c3/lib/src/NamespaceSymbol.d.ts
src/node_modules/antlr4-c3/lib/src/ParameterSymbol.d.ts
src/node_modules/antlr4-c3/lib/src/RoutineSymbol.d.ts
src/node_modules/antlr4-c3/lib/src/ScopedSymbol.d.ts
src/node_modules/antlr4-c3/lib/src/SymbolTable.d.ts
src/node_modules/antlr4-c3/lib/src/TypeAlias.d.ts
src/node_modules/antlr4-c3/lib/src/TypedSymbol.d.ts
src/node_modules/antlr4-c3/lib/src/VariableSymbol.d.ts
src/node_modules/antlr4-c3/lib/src/types.d.ts
src/node_modules/antlr4-c3/lib/src/utils.d.ts
src/node_modules/antlr4ng/LICENSE.txt
src/node_modules/antlr4ng/ReadMe.md
src/node_modules/antlr4ng/package.json
src/node_modules/antlr4ng/dist/ANTLRErrorListener.d.ts
src/node_modules/antlr4ng/dist/ANTLRErrorStrategy.d.ts
jsoniq_jupyter_lsp-1.0.0.dist-info/LICENSE
jsoniq_jupyter_lsp-1.0.0.dist-info/METADATA
jsoniq_jupyter_lsp-1.0.0.dist-info/WHEEL
jsoniq_jupyter_lsp-1.0.0.dist-info/entry_points.txt
jsoniq_jupyter_lsp-1.0.0.dist-info/top_level.txt
jsoniq_jupyter_lsp-1.0.0.dist-info/RECORD
