Metadata-Version: 2.1
Name: jsoniq-jupyter-lsp
Version: 1.0.0
Summary: Jupyter extension to support RumbleDB development in notebooks. The extension runs the language server for JSONiq to provide code auto-completion, syntax highlighting, and diagnostics.
Home-page: https://www.jsoniq.org/
Author: David-Marian Buzatu
Author-email: davidm.buzatu@gmail.com
License: Apache License 2.0
Keywords: rumble jsoniq rumbledb json IPython jupyter
Classifier: Intended Audience :: Developers
Classifier: Operating System :: OS Independent
License-File: LICENSE
